ICD_Interfaces/A429.py
ICD_Interfaces/AFDX.py
ICD_Interfaces/ANALOGUE.py
ICD_Interfaces/AcIcd.py
ICD_Interfaces/CAN.py
ICD_Interfaces/CONNECTOR.py
ICD_Interfaces/DISCRETE.py
ICD_Interfaces/EQUIPMENT.py
ICD_Interfaces/ICMP.py
ICD_Interfaces/MEM.py
ICD_Interfaces/PARTITION.py
ICD_Interfaces/RAM.py
ICD_Interfaces/SViteConfig.py
ICD_Interfaces/SpyNode.py
ICD_Interfaces/__init__.py
ICD_Interfaces-1.0.dist-info/METADATA
ICD_Interfaces-1.0.dist-info/RECORD
ICD_Interfaces-1.0.dist-info/WHEEL
ICD_Interfaces-1.0.dist-info/top_level.txt
