Metadata-Version: 2.1
Name: ICD-Interfaces
Version: 1.0
Summary: ICD_Tools interfaces
Home-page: UNKNOWN
Author: UNKNOWN
Author-email: UNKNOWN
License: UNKNOWN
Platform: UNKNOWN
Requires-Dist: mypy
